nester.py
nester_onbon-1.0.2.dist-info/METADATA
nester_onbon-1.0.2.dist-info/WHEEL
nester_onbon-1.0.2.dist-info/top_level.txt
nester_onbon-1.0.2.dist-info/RECORD
