Metadata-Version: 2.1
Name: nester-onbon
Version: 1.0.2
Summary: This is a simple demo
Home-page: http://www.onbonbx.com
Author: onbon
Author-email: wangyq@onbonbx.com
License: UNKNOWN
Platform: UNKNOWN
